{"title":"","id":1,"dateAdded":1325734040852659,"lastModified":1327087266311433,"type":"text/x-moz-place-container","root":"placesRoot","children":[{"title":"Bookmarks Menu","id":2,"parent":1,"dateAdded":1325734040856964,"lastModified":1372182500167725,"type":"text/x-moz-place-container","root":"bookmarksMenuFolder","children":[{"title":"Recently Bookmarked","id":726,"parent":2,"annos":[{"name":"Places/SmartBookmark","flags":0,"expires":4,"mimeType":null,"type":3,"value":"RecentlyBookmarked"}],"type":"text/x-moz-place","uri":"place:folder=BOOKMARKS_MENU&folder=UNFILED_BOOKMARKS&folder=TOOLBAR&sort=12&excludeQueries=1&maxResults=10&queryType=1"},{"index":1,"title":"Recent Tags","id":727,"parent":2,"annos":[{"name":"Places/SmartBookmark","flags":0,"expires":4,"mimeType":null,"type":3,"value":"RecentTags"}],"type":"text/x-moz-place","uri":"place:sort=14&type=6&maxResults=10&queryType=1"},{"index":2,"title":"","id":16,"parent":2,"dateAdded":1325734040950176,"lastModified":1325734040950176,"type":"text/x-moz-place-separator"},{"index":3,"title":"Mozilla Firefox","id":8,"parent":2,"dateAdded":1325734040938477,"lastModified":1325734040940527,"type":"text/x-moz-place-container","children":[{"title":"Help and Tutorials","id":9,"parent":8,"dateAdded":1325734040938608,"lastModified":1325734040939176,"type":"text/x-moz-place","uri":"http://www.mozilla.com/en-US/firefox/help/"},{"index":1,"title":"Customize Firefox","id":10,"parent":8,"dateAdded":1325734040939321,"lastModified":1325734040939708,"type":"text/x-moz-place","uri":"http://www.mozilla.com/en-US/firefox/customize/"},{"index":2,"title":"Get Involved","id":11,"parent":8,"dateAdded":1325734040939983,"lastModified":1325734040940340,"type":"text/x-moz-place","uri":"http://www.mozilla.com/en-US/firefox/community/"},{"index":3,"title":"About Us","id":12,"parent":8,"dateAdded":1325734040940527,"lastModified":1325734040940884,"type":"text/x-moz-place","uri":"http://www.mozilla.com/en-US/about/"}]},{"index":4,"title":"My experiences working local and remote for Mozilla « JAWS","id":78,"parent":2,"dateAdded":1325815321073183,"lastModified":1325815321073826,"type":"text/x-moz-place","uri":"http://msujaws.wordpress.com/2011/09/05/my-experiences-working-local-and-remote-for-mozilla/","charset":"UTF-8"},{"index":5,"title":"Services/NativeSync - MozillaWiki","id":140,"parent":2,"dateAdded":1326218914216529,"lastModified":1326218914230505,"type":"text/x-moz-place","uri":"https://wiki.mozilla.org/Services/NativeSync","charset":"UTF-8"},{"index":6,"title":"Services/Sync/Snippets - MozillaWiki","id":210,"parent":2,"dateAdded":1326244088162390,"lastModified":1326244088163210,"type":"text/x-moz-place","uri":"https://wiki.mozilla.org/Services/Sync/Snippets","charset":"UTF-8"},{"index":7,"title":"Coverage Report","id":276,"parent":2,"dateAdded":1326325067602685,"lastModified":1326325067603496,"type":"text/x-moz-place","uri":"file:///Users/ncalexan/Mozilla/Android/Devel/android-sync/target/site/cobertura/index.html","charset":"UTF-8"},{"index":8,"title":"a little madness » Blog Archive » Understanding the Android Build Process","id":346,"parent":2,"dateAdded":1326394240172295,"lastModified":1326394240458568,"type":"text/x-moz-place","uri":"http://www.alittlemadness.com/2010/06/07/understanding-the-android-build-process/","charset":"UTF-8"},{"index":9,"title":"What Kara's Cookin': Slow Cooker Chicken Thighs with Carrots & Potatoes","id":412,"parent":2,"dateAdded":1326695362387142,"lastModified":1326695362395742,"type":"text/x-moz-place","uri":"http://whatkarascookin.blogspot.com/2009/10/slow-cooker-chicken-thighs-with-carrots.html","charset":"UTF-8"},{"index":10,"title":"Apartments","id":541,"parent":2,"dateAdded":1328645203191114,"lastModified":1328645238806928,"type":"text/x-moz-place-container","children":[{"title":"Apartments for Rent - PadMapper Apartment Search for Oodle, Apartments.com, Rent.com, Kijiji, and Craigslist Apartments","id":554,"parent":541,"dateAdded":1328645203198223,"lastModified":1328645203198223,"type":"text/x-moz-place","uri":"http://www.padmapper.com/#"},{"index":1,"title":"975ft² - 2 Bed/2 Bath - Great Location","id":555,"parent":541,"dateAdded":1328645203198600,"lastModified":1328645203198600,"type":"text/x-moz-place","uri":"http://www.padmapper.com/show.php?type=0&id=99518109&src=main"},{"index":2,"title":"1000ft² - Fabulous Two Bedroom, Two Bathroom plus Den Condo Style Apartment","id":556,"parent":541,"dateAdded":1328645203198966,"lastModified":1328645203198966,"type":"text/x-moz-place","uri":"http://www.padmapper.com/show.php?type=0&id=100797705&src=main"},{"index":3,"title":"900ft² - Woodwards Building 2/BR 900SQFT -Parkikng Incl. Amenities","id":557,"parent":541,"dateAdded":1328645203199317,"lastModified":1328645203199317,"type":"text/x-moz-place","uri":"http://www.padmapper.com/show.php?type=0&id=99735122&src=main"},{"index":4,"title":"865ft² - 2 BED ROOM, 2 FULL BATH, LARGE PATIO","id":558,"parent":541,"dateAdded":1328645203199815,"lastModified":1328645203199815,"type":"text/x-moz-place","uri":"http://www.padmapper.com/show.php?type=0&id=101296301&src=main"},{"index":5,"title":"856ft² - Rarely Available Extra Large 1 Bedroom and Den + Office with View","id":559,"parent":541,"dateAdded":1328645203200253,"lastModified":1328645203200253,"type":"text/x-moz-place","uri":"http://www.padmapper.com/show.php?type=0&id=101336818&src=main"},{"index":6,"title":"963ft² - Crestmark I - Live by the Seawall in This Pet-Friendly 2BR Suite","id":560,"parent":541,"dateAdded":1328645203200611,"lastModified":1328645203200611,"type":"text/x-moz-place","uri":"http://www.padmapper.com/show.php?type=0&id=101047458&src=main"},{"index":7,"title":null,"id":561,"parent":541,"dateAdded":1328645203200963,"lastModified":1328645203200963,"type":"text/x-moz-place","uri":"http://www.canadahomeguide.tv/Rental"},{"index":8,"title":"900ft² - Robson Sun Deck","id":562,"parent":541,"dateAdded":1328645203201303,"lastModified":1328645203201303,"type":"text/x-moz-place","uri":"http://www.padmapper.com/show.php?type=0&id=100969089&src=main"},{"index":9,"title":"750ft² - Newly Reno'd West End 2 Bdrm w/ Laundry, Wood Floors, Granite(ID:1230)","id":563,"parent":541,"dateAdded":1328645203201657,"lastModified":1328645203201657,"type":"text/x-moz-place","uri":"http://www.padmapper.com/show.php?type=0&id=101151488&src=main"},{"index":10,"title":"1000ft² - Open Suite with Large Patio","id":564,"parent":541,"dateAdded":1328645203202005,"lastModified":1328645203202005,"type":"text/x-moz-place","uri":"http://www.padmapper.com/show.php?type=0&id=101091259&src=main"}]},{"index":11,"title":"White Bean, Sweet Potato & Pepper Ragout Recipe | Taste of Home","id":565,"parent":2,"dateAdded":1329700784875502,"lastModified":1329700784887262,"type":"text/x-moz-place","uri":"http://www.tasteofhome.com/Recipes/White-Bean--Sweet-Potato---Pepper-Ragout/Print","charset":"UTF-8"},{"index":12,"title":"Planet Emacsen","id":566,"parent":2,"dateAdded":1329711909782574,"lastModified":1329711909783847,"type":"text/x-moz-place","uri":"http://planet.emacsen.org/","charset":"UTF-8"},{"index":13,"title":"futurama","id":567,"parent":2,"dateAdded":1329975519470341,"lastModified":1329975521393752,"annos":[{"name":"bookmarkProperties/description","flags":0,"expires":4,"mimeType":null,"type":3,"value":"BinSearch.info Binary Usenet nzb Search Engine"}],"type":"text/x-moz-place","uri":"http://binsearch.info/?server=2&max=250&g=alt.binaries.multimedia.lost&a=slowpoke57%40SLOSUXgmail.com+(slowpoke)","charset":"ISO-8859-1"},{"index":14,"title":"PS3™ | Types of files that can be played","id":571,"parent":2,"dateAdded":1331444710050012,"lastModified":1331444710079170,"annos":[{"name":"bookmarkProperties/description","flags":0,"expires":4,"mimeType":null,"type":3,"value":"Sony Computer Entertainment   PS3™   Official Online Instruction Manual. Explains how to use the PS3™ system software."}],"type":"text/x-moz-place","uri":"http://manuals.playstation.net/document/en/ps3/current/video/filetypes.html","charset":"UTF-8"},{"index":15,"title":"mixed color tulips - Downtown Vancouver Florist","id":573,"parent":2,"dateAdded":1332267288028474,"lastModified":1332267288043219,"annos":[{"name":"bookmarkProperties/description","flags":0,"expires":4,"mimeType":null,"type":3,"value":"Cheerful bouquet&nbsp;of mixed colored tulips.Hand delivered by florist in Vancouver"}],"type":"text/x-moz-place","uri":"http://www.canadaflorists.com/all-occasions/130-mixed-colors-tulips-arrangement.html","charset":"UTF-8"},{"index":16,"title":"using WIP branches to save every edit - Bart's Blog","id":578,"parent":2,"dateAdded":1333557646662069,"lastModified":1333557646713612,"type":"text/x-moz-place","uri":"http://www.jukie.net/~bart/blog/save-everything-with-git-wip","charset":"ISO-8859-1"},{"index":17,"title":"Add-on SDK Documentation","id":579,"parent":2,"dateAdded":1335205765405059,"lastModified":1335205765417808,"type":"text/x-moz-place","uri":"https://addons.mozilla.org/en-US/developers/docs/sdk/latest/","charset":"UTF-8"},{"index":18,"title":"Firefox Sync Services Account","id":580,"parent":2,"dateAdded":1335299808628456,"lastModified":1335299815145898,"type":"text/x-moz-place","uri":"https://account.services.mozilla.com/","charset":"UTF-8"},{"index":19,"title":"git-code-review/git-code-review.el at master · emacsmirror/git-code-review · GitHub","id":581,"parent":2,"dateAdded":1335458459659468,"lastModified":1335458459697647,"annos":[{"name":"bookmarkProperties/description","flags":0,"expires":4,"mimeType":null,"type":3,"value":"git-code-review - Code review tool for Emacs"}],"type":"text/x-moz-place","uri":"https://github.com/emacsmirror/git-code-review/blob/master/git-code-review.el","charset":"UTF-8"},{"index":20,"title":"Mozilla Services » System Status","id":582,"parent":2,"dateAdded":1335544341258508,"lastModified":1335544341294289,"type":"text/x-moz-place","uri":"https://services.mozilla.com/status/","charset":"UTF-8"},{"index":21,"title":"DavkaBT - basketball torrents","id":586,"parent":2,"dateAdded":1336180921662447,"lastModified":1336180921665369,"annos":[{"name":"bookmarkProperties/description","flags":0,"expires":4,"mimeType":null,"type":3,"value":"Basketball BT files"}],"type":"text/x-moz-place","uri":"http://bt.davka.info/","charset":"UTF-8"},{"index":22,"title":"Setting up ZNC on Mozilla People for Limechat « Curtisville","id":587,"parent":2,"dateAdded":1336504090322246,"lastModified":1336504090371169,"type":"text/x-moz-place","uri":"https://spartiates.wordpress.com/2012/03/13/setting-up-znc-on-mozilla-people-for-limechat/","charset":"UTF-8"},{"index":23,"title":"Can't access preferences set in account-authenticator in Android - Stack Overflow","id":588,"parent":2,"dateAdded":1337818924059934,"lastModified":1337818924075763,"type":"text/x-moz-place","uri":"http://stackoverflow.com/questions/5885445/cant-access-preferences-set-in-account-authenticator-in-android","charset":"UTF-8"},{"index":24,"title":"Authenticator « Tight Lines and Tight Deadlines","id":591,"parent":2,"dateAdded":1339556311143817,"lastModified":1339556311181865,"annos":[{"name":"bookmarkProperties/description","flags":0,"expires":4,"mimeType":null,"type":3,"value":"Posts about Authenticator written by Eric Miles"}],"type":"text/x-moz-place","uri":"http://ericmiles.wordpress.com/tag/authenticator/","charset":"UTF-8"},{"index":25,"title":"Concept of SyncAdapter (android.content.AbstractThreadedSyncAdapter) - Android by Sample","id":592,"parent":2,"dateAdded":1339556911999378,"lastModified":1339556912012877,"annos":[{"name":"bookmarkProperties/description","flags":0,"expires":4,"mimeType":null,"type":3,"value":"Some random info about android platform."}],"type":"text/x-moz-place","uri":"https://sites.google.com/site/andsamples/concept-of-syncadapter-androidcontentabstractthreadedsyncadapter","charset":"UTF-8"},{"index":26,"title":"signing Fennec Releases/Fennec 4.0.1/BuildNotes - MozillaWiki","id":593,"parent":2,"dateAdded":1339620672053863,"lastModified":1339620677313742,"type":"text/x-moz-place","uri":"https://wiki.mozilla.org/Releases/Fennec_4.0.1/BuildNotes#Sign_Android","charset":"UTF-8"},{"index":27,"title":"Brian R. Bondy - Mozilla Platform Development Cheat Sheet","id":594,"parent":2,"dateAdded":1339643939303009,"lastModified":1339643939335218,"type":"text/x-moz-place","uri":"http://www.brianbondy.com/mozilla/cheatsheet/","charset":"UTF-8"},{"index":28,"title":"Epoch Converter - Unix Timestamp Converter","id":595,"parent":2,"dateAdded":1340723687624980,"lastModified":1340723687663648,"annos":[{"name":"bookmarkProperties/description","flags":0,"expires":4,"mimeType":null,"type":3,"value":"Easy epoch/Unix timestamp converter for computer programmers. Includes epoch explanation and conversion syntax in various programming languages."}],"type":"text/x-moz-place","uri":"http://www.epochconverter.com/","charset":"UTF-8"},{"index":29,"title":"android - Restart Service for App on SD Card When SD Card Is Remounted - Stack Overflow","id":596,"parent":2,"dateAdded":1340753329193545,"lastModified":1340753329205007,"type":"text/x-moz-place","uri":"http://stackoverflow.com/questions/3964375/restart-service-for-app-on-sd-card-when-sd-card-is-remounted","charset":"UTF-8"},{"index":30,"title":"Registering for Broadcast through AndroidManifest « 2cupsOfTech","id":597,"parent":2,"dateAdded":1340753825214922,"lastModified":1340753825228045,"annos":[{"name":"bookmarkProperties/description","flags":0,"expires":4,"mimeType":null,"type":3,"value":"Here is a small tip that took me a while to figure out but hopefully will save someone time and frustration. I have a BroadcastReceiver in my application that listens for network connectivity changes so the app. can resume background work on network availability. If you register for receiver in AndroidManifest.xml then you need to…"}],"type":"text/x-moz-place","uri":"http://2cupsoftech.wordpress.com/2011/01/01/registering-for-broadcast-through-androidmanifest/","charset":"UTF-8"},{"index":31,"title":"Android Developers Blog: Apps on SD Card: The Details","id":598,"parent":2,"dateAdded":1340811752825239,"lastModified":1340811752839547,"type":"text/x-moz-place","uri":"http://android-developers.blogspot.com/2010/07/apps-on-sd-card-details.html","charset":"UTF-8"},{"index":32,"title":"broadcastreceiver - Android - How to receive the BOOT signal with an application installed on sdcard? - Stack Overflow","id":599,"parent":2,"dateAdded":1340814300325394,"lastModified":1340814300339601,"type":"text/x-moz-place","uri":"http://stackoverflow.com/questions/6342867/android-how-to-receive-the-boot-signal-with-an-application-installed-on-sdcard","charset":"UTF-8"},{"index":33,"title":"Android receiver example for package install/remove/replace | Xinotes","id":600,"parent":2,"dateAdded":1340814308133104,"lastModified":1340814308134225,"type":"text/x-moz-place","uri":"http://www.xinotes.org/notes/note/1335/","charset":"UTF-8"},{"index":34,"title":"Intent | Android Developers","id":601,"parent":2,"dateAdded":1340814350631355,"lastModified":1340814350633763,"type":"text/x-moz-place","uri":"http://developer.android.com/reference/android/content/Intent.html#ACTION_EXTERNAL_APPLICATIONS_AVAILABLE","charset":"UTF-8"},{"index":35,"title":"Android installLocation and BOOT_COMPLETED - Stack Overflow","id":602,"parent":2,"dateAdded":1340814354826427,"lastModified":1340814354829868,"type":"text/x-moz-place","uri":"http://stackoverflow.com/questions/6391763/android-installlocation-and-boot-completed","charset":"UTF-8"},{"index":36,"title":"Issue 8485 - android - Documentation bug: ACTION_EXTERNAL_APPLICATIONS_AVAILABLE - Android - An Open Handset Alliance Project - Google Project Hosting","id":603,"parent":2,"dateAdded":1340814360191333,"lastModified":1340814360193442,"type":"text/x-moz-place","uri":"http://code.google.com/p/android/issues/detail?id=8485","charset":"UTF-8"},{"index":37,"title":"android - Clearing data on account removal - Stack Overflow","id":605,"parent":2,"dateAdded":1341417877059389,"lastModified":1341417877116309,"type":"text/x-moz-place","uri":"http://stackoverflow.com/questions/5748295/clearing-data-on-account-removal","charset":"UTF-8"},{"index":38,"title":"Android - Instrumentation Testing","id":606,"parent":2,"dateAdded":1341516714717592,"lastModified":1341516714738613,"type":"text/x-moz-place","uri":"http://www.netmite.com/android/mydroid/development/pdk/docs/instrumentation_testing.html","charset":"UTF-8"},{"index":39,"title":"kottke.org - home of fine hypertext products","id":607,"parent":2,"dateAdded":1341523689172289,"lastModified":1341523689173214,"type":"text/x-moz-place","uri":"http://kottke.org/","charset":"UTF-8"},{"index":40,"title":"Creating Mercurial User Repositories - MDN","id":608,"parent":2,"dateAdded":1341860216051711,"lastModified":1341860216053186,"type":"text/x-moz-place","uri":"https://developer.mozilla.org/en/Creating_Mercurial_User_Repositories","charset":"UTF-8"},{"index":41,"title":"How to uniquely identify an android Applications - Stack Overflow","id":609,"parent":2,"dateAdded":1341945094171317,"lastModified":1341945094210642,"type":"text/x-moz-place","uri":"http://stackoverflow.com/questions/7776685/how-to-uniquely-identify-an-android-applications","charset":"UTF-8"},{"index":42,"title":"BrowserID+REST brief update","id":610,"parent":2,"dateAdded":1342109585306999,"lastModified":1342109585309886,"type":"text/x-moz-place","uri":"https://mail.mozilla.org/pipermail/services-dev/2012-February/001047.html","charset":"UTF-8"},{"index":43,"title":"How BrowserID Works","id":611,"parent":2,"dateAdded":1342136284690450,"lastModified":1342136284741639,"type":"text/x-moz-place","uri":"http://lloyd.io/how-browserid-works","charset":"ISO-8859-1"},{"index":44,"title":"Guide to Implementing a Persona IdP - MDN","id":612,"parent":2,"dateAdded":1342137197274127,"lastModified":1342137197288206,"type":"text/x-moz-place","uri":"https://developer.mozilla.org/en/BrowserID/Guide_to_Implementing_a_Persona_IdP","charset":"UTF-8"},{"index":45,"title":"lexanderA » Extracting HTML from a WebView","id":614,"parent":2,"dateAdded":1342323103259458,"lastModified":1342323103301958,"type":"text/x-moz-place","uri":"http://lexandera.com/2009/01/extracting-html-from-a-webview/","charset":"UTF-8"},{"index":46,"title":"Module: JWT","id":615,"parent":2,"dateAdded":1342508584612924,"lastModified":1342508584918720,"type":"text/x-moz-place","uri":"http://www.ruby-doc.org/gems/docs/j/jwt-0.1.3/JWT.html","charset":"us-ascii"},{"index":47,"title":"JOSE JWS:Implementation — identity 1.0 documentation","id":616,"parent":2,"dateAdded":1342508669302197,"lastModified":1342508669303492,"type":"text/x-moz-place","uri":"http://hdknr.github.com/docs/identity/impl_jws.html","charset":"UTF-8"},{"index":48,"title":"Persona style primer","id":617,"parent":2,"dateAdded":1342840838396703,"lastModified":1342840844282391,"type":"text/x-moz-place","uri":"http://people.mozilla.org/~smartell/persona/","charset":"UTF-8"},{"index":49,"title":"Persona","id":618,"parent":2,"dateAdded":1343005350017361,"lastModified":1343005350065904,"type":"text/x-moz-place","uri":"http://people.mozilla.org/~smartell/persona/#typefaces","charset":"UTF-8"},{"index":50,"title":"Browse newsgroup alt.binaries.sounds.mp3.world-music","id":619,"parent":2,"dateAdded":1343241643674450,"lastModified":1343241643734146,"annos":[{"name":"bookmarkProperties/description","flags":0,"expires":4,"mimeType":null,"type":3,"value":"BinSearch.info Binary Usenet nzb Search Engine"}],"type":"text/x-moz-place","uri":"http://binsearch.info/browse.php?bg=alt.binaries.sounds.mp3.world-music&s=48343161&all=1","charset":"ISO-8859-1"},{"index":51,"title":"Android Drawables","id":620,"parent":2,"dateAdded":1343242336210686,"lastModified":1343242336212098,"type":"text/x-moz-place","uri":"http://androiddrawableexplorer.appspot.com/","charset":"UTF-8"},{"index":52,"title":"c - Using ffmpeg convert a file from one format to another - Stack Overflow","id":621,"parent":2,"dateAdded":1345083052475349,"lastModified":1345083052528755,"type":"text/x-moz-place","uri":"http://stackoverflow.com/questions/8075992/using-ffmpeg-convert-a-file-from-one-format-to-another","charset":"UTF-8"},{"index":53,"title":"Get Started on Your Fitness Program","id":622,"parent":2,"dateAdded":1345130738253293,"lastModified":1345130738293751,"annos":[{"name":"bookmarkProperties/description","flags":0,"expires":4,"mimeType":null,"type":3,"value":"Bodybuilding, weight training, nutrition - Dave Draper's IronOnline, over 2,500 pages of insight, motivation, an active community forum board, blog and wiki database."}],"type":"text/x-moz-place","uri":"http://www.davedraper.com/new-visitor-welcome.html","charset":"ISO-8859-1"},{"index":54,"title":"When SyncAdapter runs synchronization on android? - Stack Overflow","id":623,"parent":2,"dateAdded":1345157882117038,"lastModified":1345157882122312,"type":"text/x-moz-place","uri":"http://stackoverflow.com/questions/5537581/when-syncadapter-runs-synchronization-on-android","charset":"UTF-8"},{"index":55,"title":"java - Prevent network sync trigger when syncing from network in Android ContentProvider - Stack Overflow","id":624,"parent":2,"dateAdded":1345161207697752,"lastModified":1345161207702472,"type":"text/x-moz-place","uri":"http://stackoverflow.com/questions/6588770/prevent-network-sync-trigger-when-syncing-from-network-in-android-contentprovide","charset":"UTF-8"},{"index":56,"title":"New Tab","id":625,"parent":2,"dateAdded":1345504034901148,"lastModified":1345504034913520,"type":"text/x-moz-place","uri":"about:newtab","charset":"UTF-8"},{"index":57,"title":"Choosing A Bag :: One Bag","id":626,"parent":2,"dateAdded":1345738031020090,"lastModified":1345738031032552,"annos":[{"name":"bookmarkProperties/description","flags":0,"expires":4,"mimeType":null,"type":3,"value":"leisure and business travel packing list - travel light - choosing luggage"}],"type":"text/x-moz-place","uri":"http://www.onebag.com/bags.html","charset":"ISO-8859-1"},{"index":58,"title":"view - setting max width of linearlayout or other viewgroup on android - Stack Overflow","id":627,"parent":2,"dateAdded":1345844341456869,"lastModified":1345844341461826,"type":"text/x-moz-place","uri":"http://stackoverflow.com/questions/5875877/setting-max-width-of-linearlayout-or-other-viewgroup-on-android","charset":"UTF-8"},{"index":59,"title":"Storage Service — Mozilla Services","id":628,"parent":2,"dateAdded":1346193786628676,"lastModified":1346193786642411,"type":"text/x-moz-place","uri":"http://docs.services.mozilla.com/storage/index.html","charset":"UTF-8"},{"index":60,"title":"Usenet – what have you become? | 90 Percent of Everything","id":629,"parent":2,"dateAdded":1346261444148538,"lastModified":1346261444161494,"annos":[{"name":"bookmarkProperties/description","flags":0,"expires":4,"mimeType":null,"type":3,"value":"Usenet is 32 years old. You'd be forgiven for thinking that it's a near-dead, cobweb-covered discussion forum platform, but actually it's more popular today"}],"type":"text/x-moz-place","uri":"http://www.90percentofeverything.com/2012/08/28/usenet-what-have-you-become/","charset":"UTF-8"},{"index":61,"title":"bz","id":633,"parent":2,"dateAdded":1346371868103673,"lastModified":1346371915853828,"type":"text/x-moz-place","uri":"https://bugzilla.mozilla.org/show_bug.cgi?id=%s","keyword":"bz"},{"index":62,"title":"Travel Guide - MFIntranet","id":634,"parent":2,"dateAdded":1346730881976710,"lastModified":1346730882016378,"type":"text/x-moz-place","uri":"https://intranet.mozilla.org/Travel_Guide#Make_friends_with_TSA_and_your_flight_crew","charset":"UTF-8"},{"index":63,"title":"SyncStorage API v2.0 — Mozilla Services","id":635,"parent":2,"dateAdded":1346882269119018,"lastModified":1346882269158388,"type":"text/x-moz-place","uri":"http://docs.services.mozilla.com/storage/apis-2.0.html","charset":"UTF-8"},{"index":64,"title":"Digital (dis)content - Julien Simon: HOWTO: converting mkv files to play on the PS3","id":636,"parent":2,"dateAdded":1347151266359182,"lastModified":1347151266368931,"type":"text/x-moz-place","uri":"http://juliensimon.blogspot.ca/2009/01/howto-converting-mkv-files-to-play-on.html","charset":"UTF-8"},{"index":65,"title":"http://www.java-tutorial.ch/maven/maven-integration-test","id":637,"parent":2,"dateAdded":1348000545790241,"lastModified":1348000545823588,"annos":[{"name":"bookmarkProperties/description","flags":0,"expires":4,"mimeType":null,"type":3,"value":"Maven Integration Test - Maven Integration test introduction Let's imagine you have some integration test and you want to put them in your Maven test folder. The Surefire Plugin is used during the test phase of the build lifecycle to execute your Java Un"}],"type":"text/x-moz-place","uri":"http://www.java-tutorial.ch/maven/maven-integration-test","charset":"UTF-8"},{"index":66,"title":"Integration Test with Maven « Code, Just Code.","id":638,"parent":2,"dateAdded":1348003616943098,"lastModified":1348003616961229,"annos":[{"name":"bookmarkProperties/description","flags":0,"expires":4,"mimeType":null,"type":3,"value":"A collection of posts found on the internet focusing on how to tweak/enhance Maven to perform integration tests. Integration testing with maven 2.0 – by Julien Dechmann Getting Coverage For Integration Tests – by Ulrik Sandberg Integration tests with Maven (Part 1): Failsafe Plugin – by velo Unit tests are not integration tests – by…"}],"type":"text/x-moz-place","uri":"http://cchweblog.wordpress.com/2009/06/25/integration-test-with-maven/","charset":"UTF-8"},{"index":67,"title":"My life with Android :-): Controlling application separation","id":639,"parent":2,"dateAdded":1348022533225867,"lastModified":1348022533240095,"type":"text/x-moz-place","uri":"http://mylifewithandroid.blogspot.ca/2009/06/controlling-application-separation.html","charset":"UTF-8"},{"index":68,"title":"Enable communication between two Android apps via custom permissions - Stack Overflow","id":640,"parent":2,"dateAdded":1348025048976705,"lastModified":1348025048982173,"type":"text/x-moz-place","uri":"http://stackoverflow.com/questions/11800258/enable-communication-between-two-android-apps-via-custom-permissions","charset":"UTF-8"},{"index":69,"title":"Android Security : Broadcasts - Tutorials,Articles,Algorithms,Tips,Examples about Mobile (broadcasts security)","id":641,"parent":2,"dateAdded":1348093036431778,"lastModified":1348093041938162,"annos":[{"name":"bookmarkProperties/description","flags":0,"expires":4,"mimeType":null,"type":3,"value":"Activities allow applications to call each other, reusing each other’s features and allowing for replacement or improvement of individual system pieces whenever the user likes."}],"type":"text/x-moz-place","uri":"http://programming4.us/mobile/1296.aspx","charset":"UTF-8"},{"index":70,"title":"android - Sign application with several certificates - Stack Overflow","id":643,"parent":2,"dateAdded":1349217147412905,"lastModified":1349217147416637,"type":"text/x-moz-place","uri":"http://stackoverflow.com/questions/2682105/sign-application-with-several-certificates","charset":"UTF-8"},{"index":71,"title":"android:protectionLevel “signature” with multiple certificates and sharedUid - Google Groups","id":644,"parent":2,"dateAdded":1349233906585330,"lastModified":1349233906587000,"type":"text/x-moz-place","uri":"https://groups.google.com/forum/?fromgroups=#!topic/android-developers/rIENTN3VcSU","charset":"UTF-8"},{"index":72,"title":"Creating a protectionLevel Signature Service or API for other platform builders - Google Groups","id":645,"parent":2,"dateAdded":1349234054155133,"lastModified":1349234054158167,"type":"text/x-moz-place","uri":"https://groups.google.com/forum/?fromgroups=#!topic/android-platform/wSL6--Mqvyo","charset":"UTF-8"},{"index":73,"title":"core/java/android/accounts/AccountManagerService.java - platform/frameworks/base - Git at Google","id":646,"parent":2,"dateAdded":1349235376929743,"lastModified":1349235376932291,"type":"text/x-moz-place","uri":"https://android.googlesource.com/platform/frameworks/base/+/135936072b24b090fb63940aea41b408d855a4f3/core/java/android/accounts/AccountManagerService.java","charset":"UTF-8"},{"index":74,"title":"AccountManager | Android Developers","id":647,"parent":2,"dateAdded":1349235392745832,"lastModified":1349235392749783,"type":"text/x-moz-place","uri":"http://developer.android.com/intl/zh-CN/reference/android/accounts/AccountManager.html","charset":"UTF-8"},{"index":75,"title":"android - Getting package name and signatures from uid/pid of application in native client - Stack Overflow","id":648,"parent":2,"dateAdded":1349236557865722,"lastModified":1349236557871876,"type":"text/x-moz-place","uri":"http://stackoverflow.com/questions/8146986/getting-package-name-and-signatures-from-uid-pid-of-application-in-native-client","charset":"UTF-8"},{"index":76,"title":"java - Implement signature-level security on Android services with more than one allowed signature - Stack Overflow","id":649,"parent":2,"dateAdded":1349236677887002,"lastModified":1349236677893296,"type":"text/x-moz-place","uri":"http://stackoverflow.com/questions/3760593/implement-signature-level-security-on-android-services-with-more-than-one-allowe","charset":"UTF-8"},{"index":77,"title":"Multiple signatures support on APK? - Google Groups","id":650,"parent":2,"dateAdded":1349237696322767,"lastModified":1349237696325654,"type":"text/x-moz-place","uri":"https://groups.google.com/forum/?fromgroups=#!topic/android-security-discuss/npRHQzzgErM","charset":"UTF-8"},{"index":78,"title":"Fuck the Android Build Process - Bonobo","id":651,"parent":2,"dateAdded":1349237826962055,"lastModified":1349237826964262,"type":"text/x-moz-place","uri":"http://www.bonobolabs.com/fuck-the-android-build-process/","charset":"UTF-8"},{"index":79,"title":"How to make a proper button bar on ICS — Gist","id":652,"parent":2,"dateAdded":1349389547329041,"lastModified":1349389547331887,"type":"text/x-moz-place","uri":"https://gist.github.com/2348887","charset":"UTF-8"},{"index":80,"title":"Configuring a usable Android emulator - codebutler","id":653,"parent":2,"dateAdded":1349912675280243,"lastModified":1349912675305614,"type":"text/x-moz-place","uri":"http://codebutler.com/2012/10/10/configuring-a-usable-android-emualtor/","charset":"UTF-8"},{"index":81,"title":"Token Server API 1.1 · mozilla-services/tokenserver Wiki","id":654,"parent":2,"dateAdded":1349924802817885,"lastModified":1349924802858331,"annos":[{"name":"bookmarkProperties/description","flags":0,"expires":4,"mimeType":null,"type":3,"value":"The Mozilla Token Server. Contribute to tokenserver development by creating an account on GitHub."}],"type":"text/x-moz-place","uri":"https://github.com/mozilla-services/tokenserver/wiki/Token-Server-API-1.1","charset":"UTF-8"},{"index":82,"title":"Securing Pyramid with Persona and MACAuth","id":655,"parent":2,"dateAdded":1350174384203469,"lastModified":1350174384205436,"type":"text/x-moz-place","uri":"http://www.rfk.id.au/blog/entry/securing-pyramid-persona-macauth/","charset":"ISO-8859-1"},{"index":83,"title":"Exotic Data Structures","id":656,"parent":2,"dateAdded":1350276403397393,"lastModified":1350276403400301,"type":"text/x-moz-place","uri":"http://concatenative.org/wiki/view/Exotic%20Data%20Structures","charset":"UTF-8"},{"index":84,"title":"Enable Auto-sync Only When WiFi is Enabled - Tasker Wiki","id":657,"parent":2,"dateAdded":1350504838057155,"lastModified":1350504838071844,"type":"text/x-moz-place","uri":"http://tasker.wikidot.com/autosyncwifionly","charset":"UTF-8"},{"index":85,"title":"git - git-fixup-assigner.perl -- automatically decide where to \"fixup!\"","id":658,"parent":2,"dateAdded":1350512378595848,"lastModified":1350512378610039,"annos":[{"name":"bookmarkProperties/description","flags":0,"expires":4,"mimeType":null,"type":3,"value":"git-fixup-assigner.perl -- automatically decide where to \"fixup!\". While cleaning up the 'log -L' series I gathered a large number of little fixups, and decided it would be smart if git..."}],"type":"text/x-moz-place","uri":"http://git.661346.n2.nabble.com/git-fixup-assigner-perl-automatically-decide-where-to-quot-fixup-quot-td5833134.html","charset":"UTF-8"},{"index":86,"title":"Android change Horizonal Progress bar color - Stack Overflow","id":659,"parent":2,"dateAdded":1350590687673705,"lastModified":1350590687677151,"type":"text/x-moz-place","uri":"http://stackoverflow.com/questions/5745814/android-change-horizonal-progress-bar-color","charset":"UTF-8"},{"index":87,"title":"Android Developers Blog: Custom Class Loading in Dalvik","id":660,"parent":2,"dateAdded":1350794341199125,"lastModified":1350794341215285,"type":"text/x-moz-place","uri":"http://android-developers.blogspot.ca/2011/07/custom-class-loading-in-dalvik.html","charset":"UTF-8"},{"index":88,"title":"You're Missing the Point of Promises — Gist","id":662,"parent":2,"dateAdded":1350966379209731,"lastModified":1350966379211739,"type":"text/x-moz-place","uri":"https://gist.github.com/3889970","charset":"UTF-8"},{"index":89,"title":"Howto install Sun Java Runtime Environment (JRE) in Ubuntu 10.04 (Lucid Lynx) | Ubuntu Geek","id":663,"parent":2,"dateAdded":1351105469690106,"lastModified":1351105469691332,"type":"text/x-moz-place","uri":"http://www.ubuntugeek.com/how-install-sun-java-runtime-environment-jre-in-ubuntu-10-04-lucid-lynx.html","charset":"UTF-8"},{"index":90,"title":"Using Vagrant as a Team","id":664,"parent":2,"dateAdded":1351107238139743,"lastModified":1351107238140699,"type":"text/x-moz-place","uri":"http://www.jedi.be/blog/2011/03/28/using-vagrant-as-a-team/","charset":"UTF-8"},{"index":91,"title":"Installing Maven 3 on Ubuntu 10.04 LTS Server « Trial and Terror","id":665,"parent":2,"dateAdded":1351133205744831,"lastModified":1351133205805327,"annos":[{"name":"bookmarkProperties/description","flags":0,"expires":4,"mimeType":null,"type":3,"value":"Installing Maven 3 on Ubuntu 10.04 LTS Server. In preparing to upgrade a customer’s software recently I discovered there were issues with Maven version 2, so I also had to upgrade to Maven version 3. Not a whole of information available about configuration, here’s what worked for me. Download Maven 3. $ cd /home/myusername $…"}],"type":"text/x-moz-place","uri":"http://lukieb.wordpress.com/2011/02/15/installing-maven-3-on-ubuntu-10-04-lts-server/","charset":"UTF-8"},{"index":92,"title":"My life with Android :-): Observing content","id":666,"parent":2,"dateAdded":1351366249097326,"lastModified":1351366249099070,"type":"text/x-moz-place","uri":"http://mylifewithandroid.blogspot.com/2008/03/observing-content.html","charset":"UTF-8"},{"index":93,"title":"android - How to know when sync is finished? - Stack Overflow","id":667,"parent":2,"dateAdded":1351366387939841,"lastModified":1351366387944069,"type":"text/x-moz-place","uri":"http://stackoverflow.com/questions/6622316/how-to-know-when-sync-is-finished/6622884#6622884","charset":"UTF-8"},{"index":94,"title":"android - How to use CALLER_IS_SYNCADAPTER properly - Stack Overflow","id":668,"parent":2,"dateAdded":1351366433634657,"lastModified":1351366433639124,"type":"text/x-moz-place","uri":"http://stackoverflow.com/questions/6969522/how-to-use-caller-is-syncadapter-properly","charset":"UTF-8"},{"index":95,"title":"ruby - How to set an environment variable on a server with puppet? - Stack Overflow","id":669,"parent":2,"dateAdded":1351985240998877,"lastModified":1351985241035317,"type":"text/x-moz-place","uri":"http://stackoverflow.com/questions/12888499/how-to-set-an-environment-variable-on-a-server-with-puppet","charset":"UTF-8"},{"index":96,"title":"Creating Puppet types and providers is easy... - Kartar.Net","id":670,"parent":2,"dateAdded":1351989707186363,"lastModified":1351989707188630,"type":"text/x-moz-place","uri":"http://www.kartar.net/2010/02/puppet-types-and-providers-are-easy/","charset":"UTF-8"},{"index":97,"title":"ASCIIcasts - “Episode 292 - Virtual Machines with Vagrant”","id":671,"parent":2,"dateAdded":1352005902992357,"lastModified":1352005903005432,"annos":[{"name":"bookmarkProperties/description","flags":0,"expires":4,"mimeType":null,"type":3,"value":"Vagrant allows you to run your Rails application and all of its dependencies in a portable, sharable environment. Use for development, set it up as a staging server, or experiment with a production setup."}],"type":"text/x-moz-place","uri":"http://asciicasts.com/episodes/292-virtual-machines-with-vagrant","charset":"UTF-8"},{"index":98,"title":"Vagrant core no longer tied to VirtualBox | Hacker News","id":672,"parent":2,"dateAdded":1352008705125629,"lastModified":1352008705406209,"type":"text/x-moz-place","uri":"http://news.ycombinator.com/item?id=4406467","charset":"UTF-8"},{"index":99,"title":"Install Eclipse SDK 4.2.1 (Juno) on Fedora 17/16, CentOS/RHEL 6.3/5.8","id":673,"parent":2,"dateAdded":1352008832122503,"lastModified":1352008832411199,"annos":[{"name":"bookmarkProperties/description","flags":0,"expires":4,"mimeType":null,"type":3,"value":"This is guide, howto install latest Eclipse SDK 4.2.1 (Juno) on Fedora, CentOS and Red Hat (RHEL). This guide should work with Fedora 17/16/15/14/13/12, CentOS 6.3/6.2/6.1/6/5.8 and Red Hat (RHEL) 6.3/6.2/6.1/6/5.8 and even with earlier versions. Eclipse is a multi-language software development environment comprising an integrated development environment (IDE) and an extensible plug-in system. It..."}],"type":"text/x-moz-place","uri":"http://www.if-not-true-then-false.com/2010/linux-install-eclipse-on-fedora-centos-red-hat-rhel/","charset":"UTF-8"},{"index":100,"title":"NeatoCode Techniques, Supporting Low Cost Android Phones","id":674,"parent":2,"dateAdded":1352045969880937,"lastModified":1352045969892501,"annos":[{"name":"bookmarkProperties/description","flags":0,"expires":4,"mimeType":null,"type":3,"value":"Supporting Low Cost Android Phones The Android operating system now runs 75% of all smartphones shipped, covering a wide variety of different hardware and price points. Make sure you aren’t crashing..."}],"type":"text/x-moz-place","uri":"http://neatocode.tumblr.com/post/34964277213/low-cost-phones","charset":"UTF-8"},{"index":101,"title":"Stop Writing Puppet Modules That Suck","id":675,"parent":2,"dateAdded":1352048143954471,"lastModified":1352048143956845,"type":"text/x-moz-place","uri":"http://bombasticmonkey.com/2011/12/27/stop-writing-puppet-modules-that-suck/","charset":"ISO-8859-1"},{"index":102,"title":"Install Eclipse Juno and the Android SDK on Ubuntu | Mark Loiseau","id":676,"parent":2,"dateAdded":1352136443581989,"lastModified":1352136443583581,"type":"text/x-moz-place","uri":"http://blog.markloiseau.com/2012/07/install-eclipse-juno-and-android-sdk-on-ubuntu/","charset":"UTF-8"},{"index":103,"title":"Andreas Kluck: AsyncTask and AsyncTaskLoader","id":679,"parent":2,"dateAdded":1352254515052917,"lastModified":1352254515346110,"type":"text/x-moz-place","uri":"http://andreas-kluck.blogspot.com/2012/02/asynctask-and-asynctaskloader.html","charset":"UTF-8"},{"index":104,"title":"Modern techniques for implementing REST clients on Android 4.0 and below – Part 1 | neilgoodman.net","id":680,"parent":2,"dateAdded":1352254532043426,"lastModified":1352254532056489,"annos":[{"name":"bookmarkProperties/description","flags":0,"expires":4,"mimeType":null,"type":3,"value":"One of the first tasks I ever had to do as an Android developer was to make a REST client in order to communicate with a web service. It is probably one of the most common problems to solve as a mobile developer. So I thought I would spend some time discussing some of the [...]"}],"type":"text/x-moz-place","uri":"http://neilgoodman.net/2011/12/26/modern-techniques-for-implementing-rest-clients-on-android-4-0-and-below-part-1/","charset":"UTF-8"},{"index":105,"title":"Re-using Layouts with <include/> | Android Developers","id":681,"parent":2,"dateAdded":1352329590988311,"lastModified":1352329590991669,"type":"text/x-moz-place","uri":"http://developer.android.com/intl/zh-CN/training/improving-layouts/reusing-layouts.html","charset":"UTF-8"},{"index":106,"title":"http://iosched.googlecode.com/git-history/54a7cb4bb29f231992e3f8de1bc462f7b5648ae1/android/src/com/google/android/apps/iosched/ui/AccountActivity.java","id":686,"parent":2,"dateAdded":1352406269497111,"lastModified":1352406269499665,"type":"text/x-moz-place","uri":"http://iosched.googlecode.com/git-history/54a7cb4bb29f231992e3f8de1bc462f7b5648ae1/android/src/com/google/android/apps/iosched/ui/AccountActivity.java","charset":"UTF-8"},{"index":107,"title":"CowTalk","id":687,"parent":2,"dateAdded":1352677718749151,"lastModified":1352677718758886,"annos":[{"name":"bookmarkProperties/description","flags":0,"expires":4,"mimeType":null,"type":3,"value":"CowTalk - Moo-able Type for Cowtowncoder.com"}],"type":"text/x-moz-place","uri":"http://www.cowtowncoder.com/blog/blog.html","charset":"ISO-8859-1"},{"index":108,"title":"Programmer Bruce: Deserialize JSON with Jackson into Polymorphic Types - A Complete Example","id":688,"parent":2,"dateAdded":1352862508873148,"lastModified":1352862508914068,"type":"text/x-moz-place","uri":"http://programmerbruce.blogspot.ca/2011/05/deserialize-json-with-jackson-into.html","charset":"UTF-8"},{"index":109,"title":"http://www.jroller.com/RickHigh/entry/working_with_jackson_json_views","id":689,"parent":2,"dateAdded":1352874009947921,"lastModified":1352874009949885,"type":"text/x-moz-place","uri":"http://www.jroller.com/RickHigh/entry/working_with_jackson_json_views","charset":"UTF-8"},{"index":110,"title":"Writing a Custom Jackson Serializer & Deserializer - Palomino Labs Blog","id":690,"parent":2,"dateAdded":1352915927620823,"lastModified":1352915927622384,"annos":[{"name":"bookmarkProperties/description","flags":0,"expires":4,"mimeType":null,"type":3,"value":"Jackson is a mainstay of Java web development, providing\nJSON serialization & deserialization to Jersey,\nRestEasy, and Hadoop, among many\nmore. …"}],"type":"text/x-moz-place","uri":"http://blog.palominolabs.com/2012/06/05/writing-a-custom-jackson-serializer-and-deserializer/","charset":"UTF-8"},{"index":111,"title":"Git Basics: Cleaning up excess branches | Transcending Frontiers","id":691,"parent":2,"dateAdded":1353351134586391,"lastModified":1353351134611033,"annos":[{"name":"bookmarkProperties/description","flags":0,"expires":4,"mimeType":null,"type":3,"value":"We're a passionate Ruby on Rails web design & development company in Perth, Western Australia.  We specialise in beautiful, functional & accessible web applications."}],"type":"text/x-moz-place","uri":"http://blog.thefrontiergroup.com.au/2012/07/git-basics-cleaning-up-excess-branches/","charset":"UTF-8"},{"index":112,"title":"Color Hex - ColorHexa.com","id":692,"parent":2,"dateAdded":1353456028427655,"lastModified":1353456028428939,"annos":[{"name":"bookmarkProperties/description","flags":0,"expires":4,"mimeType":null,"type":3,"value":"Color hex encyclopedia providing information about any color."}],"type":"text/x-moz-place","uri":"http://www.colorhexa.com/","charset":"UTF-8"},{"index":113,"title":"Android: Configure Custom Views Via XML | Coding Geek","id":693,"parent":2,"dateAdded":1353472115279075,"lastModified":1353472115288247,"annos":[{"name":"bookmarkProperties/description","flags":0,"expires":4,"mimeType":null,"type":3,"value":"While creating custom views is as easy as subclassing android.view.View and using the full class name with the package in the layout XML file. This is how you can pass your own configurations to the custom view. If you have … Continue reading →"}],"type":"text/x-moz-place","uri":"http://codinggeekorg.wordpress.com/2011/03/07/android-configure-custom-views-via-xml/","charset":"UTF-8"},{"index":114,"title":"Android Tutorial #4.2: Passing custom attributes via XML resource files « Pocket Journey","id":694,"parent":2,"dateAdded":1353474034272254,"lastModified":1353474034284821,"annos":[{"name":"bookmarkProperties/description","flags":0,"expires":4,"mimeType":null,"type":3,"value":"In tutorial #4.1, I mentioned that we passed custom attributes for the text and image variables from the XML resource file to our custom class. This is a critical skill for performing true object-oriented programming and how to do it wasn’t obvious from Google’s Android API Demos. Luckily I was pointed to the solution myself…"}],"type":"text/x-moz-place","uri":"http://blog.infidian.com/2008/05/02/android-tutorial-42-passing-custom-variables-via-xml-resource-files/","charset":"UTF-8"},{"index":115,"title":"Java debugging tutorial - 10 tips on debugging in java with example","id":695,"parent":2,"dateAdded":1353616448477070,"lastModified":1353616448541774,"annos":[{"name":"bookmarkProperties/description","flags":0,"expires":4,"mimeType":null,"type":3,"value":"debugging in Java is real fun if you know how to debug java program in Eclipse and Netbeans. This articles share my favorite java debugging tips for debugging java program in Eclipse"}],"type":"text/x-moz-place","uri":"http://javarevisited.blogspot.ca/2011/07/java-debugging-tutorial-example-tips.html","charset":"UTF-8"},{"index":116,"title":"Java Concurrency (&c): Allocation Instrumenter for Java","id":696,"parent":2,"dateAdded":1354063587633548,"lastModified":1354063587672963,"type":"text/x-moz-place","uri":"http://jeremymanson.blogspot.com/2009/12/allocation-instrumenter-for-java_10.html","charset":"UTF-8"},{"index":117,"title":"Android’s PreferenceActivity for all API versions | Howling at the Blackmoon","id":697,"parent":2,"dateAdded":1354315002830550,"lastModified":1354315002842361,"type":"text/x-moz-place","uri":"http://www.blackmoonit.com/2012/07/all_api_prefsactivity/","charset":"UTF-8"},{"index":118,"title":"Android Performance Case Study, Falcon Pro","id":698,"parent":2,"dateAdded":1354481624053806,"lastModified":1354481624064736,"type":"text/x-moz-place","uri":"http://www.curious-creature.org/docs/android-performance-case-study-1.html","charset":"UTF-8"},{"index":119,"title":"spullara/java-future-jdk8","id":699,"parent":2,"dateAdded":1354744595229095,"lastModified":1354744595244950,"annos":[{"name":"bookmarkProperties/description","flags":0,"expires":4,"mimeType":null,"type":3,"value":"Java Future proposal for JDK8. Contribute to java-future-jdk8 development by creating an account on GitHub."}],"type":"text/x-moz-place","uri":"https://github.com/spullara/java-future-jdk8","charset":"UTF-8"},{"index":120,"title":"Cryptographic Right Answers","id":700,"parent":2,"dateAdded":1355260361678281,"lastModified":1355260361690920,"type":"text/x-moz-place","uri":"http://www.daemonology.net/blog/2009-06-11-cryptographic-right-answers.html","charset":"ISO-8859-1"},{"index":121,"title":"A Protocol for Social Login in the Age of Mobile | Pomcor","id":701,"parent":2,"dateAdded":1355416482710694,"lastModified":1355416482723637,"type":"text/x-moz-place","uri":"http://pomcor.com/2012/06/25/a-protocol-for-social-login-in-the-age-of-mobile/","charset":"UTF-8"},{"index":122,"title":"BHeapSampler: Arndt's Java Heap Analysis Tool","id":702,"parent":2,"dateAdded":1355429793257637,"lastModified":1355429793259275,"type":"text/x-moz-place","uri":"http://dr-brenschede.de/bheapsampler/","charset":"ISO-8859-15"},{"index":123,"title":"Developing Backbone.js Applications -","id":703,"parent":2,"dateAdded":1356674238657797,"lastModified":1356674238660740,"type":"text/x-moz-place","uri":"http://addyosmani.github.com/backbone-fundamentals/#setting-expectations","charset":"UTF-8"},{"index":124,"title":"The five programming books that meant most to me by David of 37signals","id":704,"parent":2,"dateAdded":1356715103384230,"lastModified":1356715103387394,"type":"text/x-moz-place","uri":"http://37signals.com/svn/posts/3375-the-five-programming-books-that-meant-most-to-me","charset":"UTF-8"},{"index":125,"title":"Beefing up the Python Shell to build apps faster and DRYer – Ben Plesser","id":705,"parent":2,"dateAdded":1357853032658892,"lastModified":1357853032669901,"annos":[{"name":"bookmarkProperties/description","flags":0,"expires":4,"mimeType":null,"type":3,"value":"One of the great mantras in Python is  avoid repetition.  And yet, when working on a Django app or with a new third party library, I often find myself stuck in the same pitiful cycle: Start the Shell; encounter a bug or unexpected behavior; close the Shell; make some changes to my code; restart the…"}],"type":"text/x-moz-place","uri":"http://benplesser.com/2013/01/10/beefing-up-the-python-shell-to-build-apps-faster-and-dryer/","charset":"UTF-8"},{"index":126,"title":"Chasing the Dream | Climate Code Foundation","id":706,"parent":2,"dateAdded":1358014792157446,"lastModified":1358014792158601,"type":"text/x-moz-place","uri":"http://climatecode.org/blog/2013/01/chasing-the-dream/","charset":"UTF-8"},{"index":127,"title":"android - how to JUnit test ContentResolver.notifyChange - Stack Overflow","id":707,"parent":2,"dateAdded":1358552041298274,"lastModified":1358552041310942,"type":"text/x-moz-place","uri":"http://stackoverflow.com/questions/11482104/how-to-junit-test-contentresolver-notifychange","charset":"UTF-8"},{"index":128,"title":"Dive into Flexbox - Bocoup","id":708,"parent":2,"dateAdded":1359394015012620,"lastModified":1359394015021786,"annos":[{"name":"bookmarkProperties/description","flags":0,"expires":4,"mimeType":null,"type":3,"value":"A blog post about CSS3, HTML5, Flexbox and Layout from Greg Smith at Bocoup."}],"type":"text/x-moz-place","uri":"http://weblog.bocoup.com/dive-into-flexbox/","charset":"UTF-8"},{"index":129,"title":"GameFAQs: LEGO Harry Potter: Years 5-7 (PS3) FAQ/Walkthrough by CyricZ","id":709,"parent":2,"dateAdded":1359516411367871,"lastModified":1359516411369606,"type":"text/x-moz-place","uri":"http://www.gamefaqs.com/ps3/631936-lego-harry-potter-years-5-7/faqs/63405","charset":"windows-1252"},{"index":130,"title":"Green Salad with Apple, Feta, Pecans and Balsamic Dressing | Tasty Kitchen: A Happy Recipe Community!","id":710,"parent":2,"dateAdded":1360001981921254,"lastModified":1360001981972079,"type":"text/x-moz-place","uri":"http://tastykitchen.com/recipes/salads/green-salad-with-apple-feta-pecans-and-balsamic-dressing/","charset":"UTF-8"},{"index":131,"title":"Editing JavaScript with Emacs — js2-mode / Projects / Mishoo's homepage","id":711,"parent":2,"dateAdded":1360193115399722,"lastModified":1360193115470152,"type":"text/x-moz-place","uri":"http://mihai.bazon.net/projects/editing-javascript-with-emacs-js2-mode","charset":"UTF-8"},{"index":132,"title":"Restoring WordPress from a backup to Dropbox using cPanel and phpMyAdmin « Michael De Wildt","id":712,"parent":2,"dateAdded":1360544534456483,"lastModified":1360544534458326,"type":"text/x-moz-place","uri":"http://www.mikeyd.com.au/2011/10/26/restoring-wordpress-from-a-backup-to-dropbox-using-cpanel-and-phpmyadmin/","charset":"UTF-8"},{"index":133,"title":"iwantmyname and github pages sitting in a tree, K I S S I N G « 70′s Futurisitic Technology","id":713,"parent":2,"dateAdded":1360550185590329,"lastModified":1360550185610390,"type":"text/x-moz-place","uri":"http://ozten.com/psto/2013/01/31/iwantmyname-and-github-pages-sitting-in-a-tree-k-i-s-s-i-n-g/","charset":"UTF-8"},{"index":134,"title":"How to write a new WebAPI in Firefox Desktop, mobile, OS - part 1 ? - Techno Barje","id":714,"parent":2,"dateAdded":1360718936964983,"lastModified":1360718936977264,"type":"text/x-moz-place","uri":"http://blog.techno-barje.fr//post/2013/02/14/how-to-write-a-webapi/","charset":"UTF-8"},{"index":135,"title":"Apprentice Alf’s Blog | Everything you ever wanted to know about DRM and ebooks, but were afraid to ask.","id":715,"parent":2,"dateAdded":1360739516336806,"lastModified":1360739516339433,"annos":[{"name":"bookmarkProperties/description","flags":0,"expires":4,"mimeType":null,"type":3,"value":"Everything you ever wanted to know about DRM and ebooks, but were afraid to ask. (by Apprentice Alf)"}],"type":"text/x-moz-place","uri":"http://apprenticealf.wordpress.com/","charset":"UTF-8"},{"index":136,"title":"dotEPUB — Application Programming Interface (API)","id":716,"parent":2,"dateAdded":1360739969776122,"lastModified":1360739969777732,"annos":[{"name":"bookmarkProperties/description","flags":0,"expires":4,"mimeType":null,"type":3,"value":"dotEPUB Application Programming Interface (API) brings the power of dotEPUB, the tool for automatic conversion to e-book, to the developer community"}],"type":"text/x-moz-place","uri":"http://dotepub.com/api/?lang=en","charset":"UTF-8"},{"index":137,"title":"Markdown.css - make HTML look like plain-text","id":717,"parent":2,"dateAdded":1360777117888444,"lastModified":1360777117889781,"type":"text/x-moz-place","uri":"http://mrcoles.com/demo/markdown-css/","charset":"UTF-8"},{"index":138,"title":"mxr","id":718,"parent":2,"dateAdded":1360870360143024,"lastModified":1360870368826215,"type":"text/x-moz-place","uri":"http://mxr.mozilla.org/mozilla-central/find?text=%s&string=","keyword":"mxr","charset":"UTF-8"},{"index":139,"title":"Curious » REST-esting with cURL","id":719,"parent":2,"dateAdded":1360881709654592,"lastModified":1360881709655483,"type":"text/x-moz-place","uri":"http://blogs.plexibus.com/2009/01/15/rest-esting-with-curl/","charset":"UTF-8"},{"index":140,"title":"Smallest Federated Wiki Videos","id":720,"parent":2,"dateAdded":1360960163634017,"lastModified":1360960163635146,"annos":[{"name":"bookmarkProperties/description","flags":0,"expires":4,"mimeType":null,"type":3,"value":"Screencasts and videos about the Smallest Federated Wiki project hosted on GitHub."}],"type":"text/x-moz-place","uri":"http://wardcunningham.github.com/","charset":"ISO-8859-1"},{"index":141,"title":"mxr","id":721,"parent":2,"dateAdded":1361221401819601,"lastModified":1361221405061190,"type":"text/x-moz-place","uri":"http://mxr.mozilla.org/mozilla-central/find?text=%s&string=","keyword":"mxr","charset":"UTF-8"},{"index":142,"title":"Search Binsearch -- Usenet search engine","id":722,"parent":2,"dateAdded":1361424209244018,"lastModified":1361424213380285,"annos":[{"name":"bookmarkProperties/description","flags":0,"expires":4,"mimeType":null,"type":3,"value":"BinSearch.info Binary Usenet Search Engine - Binsearch -- Usenet search engine"}],"type":"text/x-moz-place","uri":"https://www.binsearch.info/index.php?adv_sort=date?q=%s&m=&max=25&adv_g=&adv_age=999&adv_sort=date&minsize=&maxsize=&font=&postdate=","keyword":"bs"},{"index":143,"title":"Stephen Colebourne's blog: Javadoc coding standards","id":723,"parent":2,"dateAdded":1361563105321950,"lastModified":1361563105333129,"type":"text/x-moz-place","uri":"http://blog.joda.org/2012/11/javadoc-coding-standards.html","charset":"UTF-8"},{"index":144,"title":"About","id":724,"parent":2,"dateAdded":1361648566783220,"lastModified":1361648566784873,"annos":[{"name":"bookmarkProperties/description","flags":0,"expires":4,"mimeType":null,"type":3,"value":"Welcome to Canadian Couch Potato. This blog is designed for Canadians who want to learn more about investing using index mutual funds and exchange-traded funds (ETFs). In 2011, it was selected by The Globe and Mail as the best investing"}],"type":"text/x-moz-place","uri":"http://canadiancouchpotato.com/about/","charset":"UTF-8"},{"index":145,"title":"Search ExecutableFile - DXR Search","id":728,"parent":2,"dateAdded":1361906623907738,"lastModified":1361906626469619,"type":"text/x-moz-place","uri":"http://dxr.mozilla.org/search?tree=mozilla-central&q=%s&redirect=true","keyword":"dxr"},{"index":146,"title":"GNU `make'","id":729,"parent":2,"dateAdded":1362005430251286,"lastModified":1362005430291911,"annos":[{"name":"bookmarkProperties/description","flags":0,"expires":4,"mimeType":null,"type":3,"value":"GNU `make'"}],"type":"text/x-moz-place","uri":"https://www.gnu.org/software/make/manual/make.html#File-Name-Functions","charset":"ISO-8859-1"},{"index":147,"title":"4.2 Built-in Functions","id":730,"parent":2,"dateAdded":1362005859009987,"lastModified":1362005859012227,"type":"text/x-moz-place","uri":"http://www.makelinux.net/make3/make3-CHP-4-SECT-2","charset":"UTF-8"},{"index":148,"title":"GitHub Flavored Markdown - Live Preview","id":731,"parent":2,"dateAdded":1363219941255814,"lastModified":1363219941257446,"type":"text/x-moz-place","uri":"http://tmpvar.com/markdown.html","charset":"UTF-8"},{"index":149,"title":"Search Mozilla Developer Network","id":732,"parent":2,"dateAdded":1364924243737711,"lastModified":1364924247153511,"type":"text/x-moz-place","uri":"https://developer.mozilla.org/en-US/search?q=%s","keyword":"mdn"},{"index":150,"title":"nerdy + lanky | Reverse SSH tunneling: easier than port forwarding!","id":733,"parent":2,"dateAdded":1365015082395504,"lastModified":1365015082404952,"annos":[{"name":"bookmarkProperties/description","flags":0,"expires":4,"mimeType":null,"type":3,"value":"Reverse SSH tunneling: easier than port forwarding! Imagine you’re developing a web application using a framework like Rails. You’ve got your development server fired up and are regularly reloading..."}],"type":"text/x-moz-place","uri":"http://bbrinck.com/post/2318562750/reverse-ssh-tunneling-easier-than-port-forwarding","charset":"UTF-8"},{"index":151,"title":"SSH Remote Local Port Tunneling","id":734,"parent":2,"dateAdded":1365015090265210,"lastModified":1365015102598783,"type":"text/x-moz-place","uri":"http://blog.bstpierre.org/category/ssh","charset":"UTF-8"},{"index":152,"title":"Writing a Firefox Protocol Handler | Mikes Musings","id":735,"parent":2,"dateAdded":1365046947910424,"lastModified":1365046947919260,"type":"text/x-moz-place","uri":"http://mike.kaply.com/2011/01/18/writing-a-firefox-protocol-handler/","charset":"UTF-8"},{"index":153,"title":"Writing a Firefox Protocol Handler | Mikes Musings","id":736,"parent":2,"dateAdded":1365052672766619,"lastModified":1365052672768027,"type":"text/x-moz-place","uri":"http://mike.kaply.com/2011/01/18/writing-a-firefox-protocol-handler/#","charset":"UTF-8"},{"index":154,"title":"Born Geek » Automatic Firefox Extension Updates","id":737,"parent":2,"dateAdded":1365365848793970,"lastModified":1365365848802894,"type":"text/x-moz-place","uri":"http://www.borngeek.com/firefox/automatic-firefox-extension-updates/","charset":"UTF-8"},{"index":155,"title":"javascript - firefox add-on develop | rewrite browser.xul - Stack Overflow","id":738,"parent":2,"dateAdded":1365374000806198,"lastModified":1365374000812850,"type":"text/x-moz-place","uri":"http://stackoverflow.com/questions/15281059/firefox-add-on-develop-rewrite-browser-xul","charset":"UTF-8"},{"index":156,"title":"javascript - Save website image using a Firefox Addon (SDK) - Stack Overflow","id":739,"parent":2,"dateAdded":1365392438069801,"lastModified":1365392438076702,"type":"text/x-moz-place","uri":"http://stackoverflow.com/questions/14048689/save-website-image-using-a-firefox-addon-sdk","charset":"UTF-8"},{"index":157,"title":"Removing the installation warning from a self hosted Firefox add-on - Stack Overflow","id":740,"parent":2,"dateAdded":1365393644860861,"lastModified":1365393644866455,"type":"text/x-moz-place","uri":"http://stackoverflow.com/questions/9214525/removing-the-installation-warning-from-a-self-hosted-firefox-add-on","charset":"UTF-8"},{"index":158,"title":"Andriy Redko {devmind}: Using Delayed queues in practice","id":741,"parent":2,"dateAdded":1365448316434776,"lastModified":1365448316453698,"type":"text/x-moz-place","uri":"http://aredko.blogspot.com/2012/04/using-delayed-queues-in-practice.html","charset":"UTF-8"},{"index":159,"title":"sendBroadcast | Just An Application","id":742,"parent":2,"dateAdded":1365812755082941,"lastModified":1365812755085054,"annos":[{"name":"bookmarkProperties/description","flags":0,"expires":4,"mimeType":null,"type":3,"value":"Posts about sendBroadcast written by Simon Lewis"}],"type":"text/x-moz-place","uri":"http://justanapplication.wordpress.com/tag/sendbroadcast/","charset":"UTF-8"},{"index":160,"title":"The CommonsBlog — Broadcast Regression Confirmed","id":743,"parent":2,"dateAdded":1365899401206534,"lastModified":1365899401219221,"annos":[{"name":"bookmarkProperties/description","flags":0,"expires":4,"mimeType":null,"type":3,"value":"Mark Murphy's CommonsBlog"}],"type":"text/x-moz-place","uri":"http://commonsware.com/blog/2011/07/13/boot-completed-regression-confirmed.html","charset":"UTF-8"},{"index":161,"title":"android - Sync Adapter without Account - Stack Overflow","id":744,"parent":2,"dateAdded":1365996379329358,"lastModified":1365996379334963,"type":"text/x-moz-place","uri":"http://stackoverflow.com/questions/5146272/sync-adapter-without-account","charset":"UTF-8"},{"index":162,"title":"Android : periodic tasks","id":745,"parent":2,"dateAdded":1365997416372069,"lastModified":1365997416373270,"type":"text/x-moz-place","uri":"http://sriram-iyengar.blogspot.ca/2011/05/android-periodic-tasks.html","charset":"UTF-8"},{"index":163,"title":"android - SyncAdapter Without an Account - Stack Overflow","id":746,"parent":2,"dateAdded":1365998075371448,"lastModified":1365998075658533,"type":"text/x-moz-place","uri":"http://stackoverflow.com/questions/8554680/syncadapter-without-an-account","charset":"UTF-8"},{"index":164,"title":"Writing xpcshell-based unit tests | MDN","id":747,"parent":2,"dateAdded":1366133150551700,"lastModified":1366133150589178,"annos":[{"name":"bookmarkProperties/description","flags":0,"expires":4,"mimeType":null,"type":3,"value":"The xpcshell tool can be used to test certain kinds of functionality. Anything available to the XPCOM layer (through scriptable interfaces) can be tested with xpcshell. See Mozilla automated testing and pages tagged \"automated testing\" for pointers to more information."}],"type":"text/x-moz-place","uri":"https://developer.mozilla.org/en-US/docs/Writing_xpcshell-based_unit_tests","charset":"UTF-8"},{"index":165,"title":"GNU Make --- Rules of Makefiles","id":748,"parent":2,"dateAdded":1366349014261532,"lastModified":1366349014272800,"type":"text/x-moz-place","uri":"http://mad-scientist.net/make/rules.html","charset":"windows-1252"},{"index":166,"title":"Responsive Web Design Patterns | This Is Responsive","id":749,"parent":2,"dateAdded":1366406516090441,"lastModified":1366406516091286,"type":"text/x-moz-place","uri":"http://bradfrost.github.io/this-is-responsive/patterns.html","charset":"UTF-8"},{"index":167,"title":"automation - How can I unlock the screen programmatically in Android? - Stack Overflow","id":750,"parent":2,"dateAdded":1366751324192364,"lastModified":1366751324214380,"type":"text/x-moz-place","uri":"http://stackoverflow.com/questions/1959012/how-can-i-unlock-the-screen-programmatically-in-android","charset":"UTF-8"},{"index":168,"title":"Mochitest | MDN","id":751,"parent":2,"dateAdded":1366759218751677,"lastModified":1366759218755782,"annos":[{"name":"bookmarkProperties/description","flags":0,"expires":4,"mimeType":null,"type":3,"value":"Mochitest is an automated testing framework built on top of the MochiKit JavaScript libraries. It's just one of the automated regression testing frameworks used by Mozilla. Tests report success or failure to the test harness using JavaScript function calls."}],"type":"text/x-moz-place","uri":"https://developer.mozilla.org/en-US/docs/Mochitest#Asynchronous_Tests","charset":"UTF-8"},{"index":169,"title":"NBA Playoffs: San Antonio Spurs vs Los Angeles Lakers Live Stream Online","id":752,"parent":2,"dateAdded":1366861688021856,"lastModified":1366861688024774,"annos":[{"name":"bookmarkProperties/description","flags":0,"expires":4,"mimeType":null,"type":3,"value":"Watch\tNBA Playoffs: San Antonio Spurs vs Los Angeles Lakers live stream online for free with high quality stream.Live Basketball\tNBA Playoffs: San Antonio Spurs vs Los Angeles Lakers Stream Online.If you are searching place to watch Basketball\tNBA Playoffs: San Antonio Spurs vs Los Angeles Lakers.Watch\tNBA Playoffs: San Antonio Spurs vs Los Angeles Lakers online streaming link 1 live for 100% free."}],"type":"text/x-moz-place","uri":"http://www.vipbox.tv/basketball/149959/1/nba-playoffs:-san-antonio-spurs-vs-los-angeles-lakers-live-stream-online.html","charset":"UTF-8"},{"index":170,"title":"NBA Live Stream Online | Watch NBA Online | Watch NCCAB Online","id":753,"parent":2,"dateAdded":1366861749809031,"lastModified":1366861749816935,"annos":[{"name":"bookmarkProperties/description","flags":0,"expires":4,"mimeType":null,"type":3,"value":"Dont miss your favorite NBA team game , NBA Live Stream on VIPBox. Enjoy live basketball streaming including games from the NBA.Euro League basketball games online"}],"type":"text/x-moz-place","uri":"http://www.vipbox.tv/sports/basketball.html","charset":"UTF-8"},{"index":171,"title":"Watch Reading and Reviewing Code - Benjamin Smedberg | fsossseneca Episodes | Videos | Blip","id":754,"parent":2,"dateAdded":1366920869316935,"lastModified":1366920869331077,"annos":[{"name":"bookmarkProperties/description","flags":0,"expires":4,"mimeType":null,"type":3,"value":"This is a video from the 2007 Seneca College FSOSS symposium."}],"type":"text/x-moz-place","uri":"http://blip.tv/fsossseneca/reading-and-reviewing-code-benjamin-smedberg-452076","charset":"UTF-8"},{"index":172,"title":"Mmm... sandwiches. - Imgur","id":755,"parent":2,"dateAdded":1367006280720223,"lastModified":1367006280760950,"annos":[{"name":"bookmarkProperties/description","flags":0,"expires":4,"mimeType":null,"type":3,"value":"Imgur is used to share photos with social networks and online communities, and has the funniest pictures from all over the Internet."}],"type":"text/x-moz-place","uri":"http://imgur.com/gallery/JCAw33u","charset":"UTF-8"},{"index":173,"title":"Alice Waters' Shaved Fennel Salad  - blog - Mother Would Know - recipes & cooking tips","id":756,"parent":2,"dateAdded":1367205728337890,"lastModified":1367205728348395,"annos":[{"name":"bookmarkProperties/description","flags":0,"expires":4,"mimeType":null,"type":3,"value":"easy recipes, money saving tips, cooking advice"}],"type":"text/x-moz-place","uri":"http://motherwouldknow.com/journal/alice-waters-shaved-fennel-salad.html","charset":"UTF-8"},{"index":174,"title":"System monitor in Emacs mode-line | I do robots","id":757,"parent":2,"dateAdded":1367269009037611,"lastModified":1367269009047831,"annos":[{"name":"bookmarkProperties/description","flags":0,"expires":4,"mimeType":null,"type":3,"value":"(by Kajtek)"}],"type":"text/x-moz-place","uri":"http://idorobots.org/2012/10/10/emacs-mode-line/","charset":"UTF-8"},{"index":175,"title":"kiwanami/emacs-deferred · GitHub","id":758,"parent":2,"dateAdded":1367269598714076,"lastModified":1367269598733294,"annos":[{"name":"bookmarkProperties/description","flags":0,"expires":4,"mimeType":null,"type":3,"value":"emacs-deferred - Simple asynchronous functions for emacs lisp"}],"type":"text/x-moz-place","uri":"https://github.com/kiwanami/emacs-deferred","charset":"UTF-8"},{"index":176,"title":"Backing Up Gmail messages with offlineimap","id":759,"parent":2,"dateAdded":1367351821185617,"lastModified":1367351821187777,"type":"text/x-moz-place","uri":"http://bluishcoder.co.nz/2013/04/30/backing_up_gmail_messages_with_offlineimap.html","charset":"UTF-8"},{"index":177,"title":"Wilfred Hughes | High signal, Low Noise","id":760,"parent":2,"dateAdded":1367355789152713,"lastModified":1367355789237439,"type":"text/x-moz-place","uri":"http://www.wilfred.me.uk/blog/2012/07/30/why-markdown-is-not-my-favourite-language/","charset":"UTF-8"},{"index":178,"title":"tools: files","id":761,"parent":2,"dateAdded":1367519876046033,"lastModified":1367519876049074,"type":"text/x-moz-place","uri":"https://hg.mozilla.org/build/tools/file/tip/sut_tools","charset":"UTF-8"},{"index":179,"title":"How to tie an amazing tie. The \"Eldredge tie knot\" - Imgur","id":762,"parent":2,"dateAdded":1367714844913765,"lastModified":1367714844957466,"annos":[{"name":"bookmarkProperties/description","flags":0,"expires":4,"mimeType":null,"type":3,"value":"Imgur is used to share photos with social networks and online communities, and has the funniest pictures from all over the Internet."}],"type":"text/x-moz-place","uri":"http://imgur.com/r/pics/8ug05FA","charset":"UTF-8"},{"index":180,"title":"InstrumentationTestRunner | Android Developers","id":763,"parent":2,"dateAdded":1367870082939797,"lastModified":1367870083450315,"type":"text/x-moz-place","uri":"http://developer.android.com/reference/android/test/InstrumentationTestRunner.html","charset":"UTF-8"},{"index":181,"title":"Advogato: Blog for wlach","id":764,"parent":2,"dateAdded":1367952104298040,"lastModified":1367952104299570,"type":"text/x-moz-place","uri":"http://www.advogato.org/person/wlach/diary.html?start=130","charset":"UTF-8"},{"index":182,"title":"Gregory Szorc's Digital Home","id":765,"parent":2,"dateAdded":1368399201199184,"lastModified":1368399201201924,"type":"text/x-moz-place","uri":"http://gregoryszorc.com/blog/2013/05/12/thoughts-on-mercurial-(and-git)/","charset":"UTF-8"},{"index":183,"title":"android - Is there a way to merge two or more .dex files into one .dex file using Scala? - Stack Overflow","id":766,"parent":2,"dateAdded":1368488210575720,"lastModified":1368488210616940,"type":"text/x-moz-place","uri":"http://stackoverflow.com/questions/11257378/is-there-a-way-to-merge-two-or-more-dex-files-into-one-dex-file-using-scala","charset":"UTF-8"},{"index":184,"title":"Making String Changes | MDN","id":767,"parent":2,"dateAdded":1368545957712910,"lastModified":1368545957717281,"annos":[{"name":"bookmarkProperties/description","flags":0,"expires":4,"mimeType":null,"type":3,"value":"Making a change to a string in Firefox can have impact on localizations. If you're making a change to a string, you must follow these guidelines."}],"type":"text/x-moz-place","uri":"https://developer.mozilla.org/en-US/docs/Making_String_Changes","charset":"UTF-8"},{"index":185,"title":"Reducing the size of your APK – A Beta-ful Life","id":768,"parent":2,"dateAdded":1368573594005143,"lastModified":1368573594020011,"type":"text/x-moz-place","uri":"http://www.betaful.com/2012/01/reducing-the-size-of-your-apk/","charset":"UTF-8"},{"index":186,"title":"Pork Chops with Cider-Dijon Pan Sauce - Fine Cooking Recipes, Techniques and Tips","id":769,"parent":2,"dateAdded":1368587699309147,"lastModified":1368587699311902,"annos":[{"name":"bookmarkProperties/description","flags":0,"expires":4,"mimeType":null,"type":3,"value":"How to make Pork Chops with Cider-Dijon Pan Sauce with 4 center-cut bone-in pork chops (2 lb.)"}],"type":"text/x-moz-place","uri":"http://www.finecooking.com/recipes/pork-chops-cider-dijon-pan-sauce.aspx","charset":"UTF-8"},{"index":187,"title":"svn - Revision 200165: /trunk/src/build/android/gyp","id":770,"parent":2,"dateAdded":1368594507921194,"lastModified":1368594507923305,"type":"text/x-moz-place","uri":"http://src.chromium.org/svn/trunk/src/build/android/gyp/","charset":"UTF-8"},{"index":188,"title":"android-tools/adbrsync.py at master · jsharkey/android-tools · GitHub","id":771,"parent":2,"dateAdded":1368738125462011,"lastModified":1368738125493613,"annos":[{"name":"bookmarkProperties/description","flags":0,"expires":4,"mimeType":null,"type":3,"value":"android-tools - Random Android scripts"}],"type":"text/x-moz-place","uri":"https://github.com/jsharkey/android-tools/blob/master/adbrsync.py","charset":"UTF-8"},{"index":189,"title":"AndroidXref - News","id":772,"parent":2,"dateAdded":1368824030121026,"lastModified":1368824030186634,"type":"text/x-moz-place","uri":"http://androidxref.com/","charset":"UTF-8"},{"index":190,"title":"why I run shells inside Emacs","id":773,"parent":2,"dateAdded":1369351786608442,"lastModified":1369351786610405,"type":"text/x-moz-place","uri":"http://snarfed.org/why_i_run_shells_inside_emacs","charset":"UTF-8"},{"index":191,"title":"Bugzilla Todos","id":774,"parent":2,"dateAdded":1369412937873159,"lastModified":1369412937874380,"type":"text/x-moz-place","uri":"http://harthur.github.io/bugzilla-todos/","charset":"windows-1252"},{"index":192,"title":"Android UIDs and GIDs - Android Wiki","id":775,"parent":2,"dateAdded":1369429510988354,"lastModified":1369429510989317,"type":"text/x-moz-place","uri":"http://android-dls.com/wiki/index.php?title=Android_UIDs_and_GIDs","charset":"UTF-8"},{"index":193,"title":"Mercurial workflows: local development work | Jimmy Bogard's Blog","id":777,"parent":2,"dateAdded":1369778550917231,"lastModified":1369778550979959,"type":"text/x-moz-place","uri":"http://lostechies.com/jimmybogard/2010/07/09/mercurial-workflows-local-development-work/","charset":"UTF-8"},{"index":194,"title":"ipc - Android ResultReceiver across packages - Stack Overflow","id":778,"parent":2,"dateAdded":1369788285107656,"lastModified":1369788285114054,"type":"text/x-moz-place","uri":"http://stackoverflow.com/questions/5743485/android-resultreceiver-across-packages","charset":"UTF-8"},{"index":195,"title":"EmacsWiki: dvc-init.el","id":779,"parent":2,"dateAdded":1369869548077609,"lastModified":1369869548091590,"type":"text/x-moz-place","uri":"http://www.emacswiki.org/emacs/dvc-init.el","charset":"UTF-8"},{"index":196,"title":"SoftwareSwirl: GNU make trick for handling long lists","id":780,"parent":2,"dateAdded":1369955958279317,"lastModified":1369955958290005,"type":"text/x-moz-place","uri":"http://softwareswirl.blogspot.ca/2009/10/gnu-make-trick-for-handling-long-lists.html","charset":"UTF-8"},{"index":197,"title":"A faster way to delete millions of files in a directory","id":781,"parent":2,"dateAdded":1370053987733905,"lastModified":1370053987745260,"type":"text/x-moz-place","uri":"http://linuxnote.net/jianingy/en/linux/a-fast-way-to-remove-huge-number-of-files.html","charset":"UTF-8"},{"index":198,"title":"A Complete Guide to Mastering Eshell | Mastering Emacs","id":782,"parent":2,"dateAdded":1370228359876868,"lastModified":1370228359945322,"annos":[{"name":"bookmarkProperties/description","flags":0,"expires":4,"mimeType":null,"type":3,"value":"There are several shells for Emacs, but none can match the versatility and integration with Emacs like Eshell."}],"type":"text/x-moz-place","uri":"http://www.masteringemacs.org/articles/2010/12/13/complete-guide-mastering-eshell/","charset":"UTF-8"},{"index":199,"title":"ssl - Java SSLException: hostname in certificate didn't match - Stack Overflow","id":784,"parent":2,"dateAdded":1370470358162523,"lastModified":1370470358455737,"type":"text/x-moz-place","uri":"http://stackoverflow.com/questions/7256955/java-sslexception-hostname-in-certificate-didnt-match","charset":"UTF-8"},{"index":200,"title":"Services/Process/MergingBetweenBranches - MozillaWiki","id":785,"parent":2,"dateAdded":1370622311919952,"lastModified":1370622311928276,"type":"text/x-moz-place","uri":"https://wiki.mozilla.org/Services/Process/MergingBetweenBranches","charset":"UTF-8"},{"index":201,"title":"checkbox - Android CheckBoxPreference title color - Stack Overflow","id":786,"parent":2,"dateAdded":1370969467511680,"lastModified":1370969467540598,"type":"text/x-moz-place","uri":"http://stackoverflow.com/questions/12004326/android-checkboxpreference-title-color","charset":"UTF-8"},{"index":202,"title":"Report: 3.5% of clocks are over an hour out on Android - OpenSignal","id":788,"parent":2,"dateAdded":1371223881733796,"lastModified":1371223881748003,"annos":[{"name":"bookmarkProperties/description","flags":0,"expires":4,"mimeType":null,"type":3,"value":"Report: 3.5% of clocks are over an hour out on Android"}],"type":"text/x-moz-place","uri":"http://opensignal.com/reports/timestamps/","charset":"UTF-8"},{"index":203,"title":"android - armeabi and armeabi-v7a folder - Stack Overflow","id":789,"parent":2,"dateAdded":1371225118874641,"lastModified":1371225118880549,"type":"text/x-moz-place","uri":"http://stackoverflow.com/questions/6249501/armeabi-and-armeabi-v7a-folder","charset":"UTF-8"},{"index":204,"title":"Android : Watchdog is killing system server","id":790,"parent":2,"dateAdded":1371488678671601,"lastModified":1371488678690135,"type":"text/x-moz-place","uri":"http://debuggingisfun.blogspot.ca/2010/06/android-watchdog-is-killing-system.html","charset":"UTF-8"},{"index":205,"title":"mxrf","id":791,"parent":2,"dateAdded":1372093153676433,"lastModified":1372093159720692,"type":"text/x-moz-place","uri":"http://mxr.mozilla.org/mozilla-central/find?string=%s&tree=mozilla-central&hint=","keyword":"mxrf","charset":"UTF-8"},{"index":206,"title":"Kohlrabi-Radish Slaw with Cumin and Cilantro","id":792,"parent":2,"dateAdded":1372095752043691,"lastModified":1372095753865208,"annos":[{"name":"bookmarkProperties/description","flags":0,"expires":4,"mimeType":null,"type":3,"value":"To speed up the vegetable prep, use the grating and slicing blades on a food processor for the radishes, carrots, and cabbage, and the julienne cutter on a mandoline for the kohlrabi."}],"type":"text/x-moz-place","uri":"http://www.finecooking.com/recipes/kohlrabi-radish-slaw-cumin-cilantro.aspx","charset":"UTF-8"},{"index":207,"title":"Browse newsgroup alt.binaries.e-book.flood","id":793,"parent":2,"dateAdded":1372130987327849,"lastModified":1372130987341475,"annos":[{"name":"bookmarkProperties/description","flags":0,"expires":4,"mimeType":null,"type":3,"value":"BinSearch.info Binary Usenet nzb Search Engine"}],"type":"text/x-moz-place","uri":"https://www.binsearch.info/browse.php?bg=alt.binaries.e-book.flood&s=97070246&all=1&server=2","charset":"windows-1252"},{"index":208,"title":"MoPad: FirefoxWalkthrough","id":794,"parent":2,"dateAdded":1372182500167725,"lastModified":1372182500174378,"type":"text/x-moz-place","uri":"https://etherpad.mozilla.org/FirefoxWalkthrough","charset":"UTF-8"}]},{"index":1,"title":"Bookmarks Toolbar","id":3,"parent":1,"dateAdded":1325734040860105,"lastModified":1371090808886470,"annos":[{"name":"bookmarkProperties/description","flags":0,"expires":4,"mimeType":null,"type":3,"value":"Add bookmarks to this folder to see them displayed on the Bookmarks Toolbar"}],"type":"text/x-moz-place-container","root":"toolbarFolder","children":[{"title":"Most Visited","id":725,"parent":3,"annos":[{"name":"Places/SmartBookmark","flags":0,"expires":4,"mimeType":null,"type":3,"value":"MostVisited"}],"type":"text/x-moz-place","uri":"place:sort=8&maxResults=10"},{"index":1,"title":"bugs-nalexander","id":539,"parent":3,"dateAdded":1328311414357943,"lastModified":1332868660484201,"type":"text/x-moz-place","uri":"https://bugzilla.mozilla.org/buglist.cgi?list_id=2691834;classification=Client%20Software;emailtype1=substring;emailassigned_to1=1;query_format=advanced;bug_status=UNCONFIRMED;bug_status=NEW;bug_status=ASSIGNED;bug_status=REOPENED;email1=nalexande;component=Android%20Sync;product=Mozilla%20Services"},{"index":2,"title":"a-s bug","id":590,"parent":3,"dateAdded":1339176609002878,"lastModified":1340037890892517,"type":"text/x-moz-place","uri":"https://bugzilla.mozilla.org/enter_bug.cgi?alias=&assigned_to=nobody%40mozilla.org&blocked=&bug_file_loc=http%3A%2F%2F&bug_severity=normal&bug_status=NEW&cf_blocking_basecamp=---&cf_blocking_fennec=---&cf_blocking_fennec10=---&cf_blocking_kilimanjaro=---&cf_crash_signature=&cf_status_esr10=---&cf_status_firefox13=---&cf_status_firefox14=---&cf_status_firefox15=---&cf_status_firefox16=---&cf_tracking_esr10=---&cf_tracking_firefox13=---&cf_tracking_firefox14=---&cf_tracking_firefox15=---&cf_tracking_firefox16=---&comment=&component=Android%20Sync&contenttypeentry=&contenttypemethod=autodetect&contenttypeselection=text%2Fplain&data=&defined_groups=1&dependson=&description=&flag_type-325=X&flag_type-37=X&flag_type-4=X&flag_type-607=X&flag_type-708=X&flag_type-720=X&flag_type-721=X&flag_type-737=X&flag_type-780=X&flag_type-781=X&form_name=enter_bug&keywords=&maketemplate=Remember%20values%20as%20bookmarkable%20template&op_sys=Android&priority=--&product=Mozilla%20Services&qa_contact=android-sync%40services.bugs&rep_platform=All&requestee_type-325=&requestee_type-4=&requestee_type-607=&requestee_type-781=&short_desc=&status_whiteboard=&target_milestone=---&version=unspecified"},{"index":3,"title":"mach P?","id":642,"parent":3,"dateAdded":1348951314830363,"lastModified":1348951322987056,"type":"text/x-moz-place","uri":"https://bugzilla.mozilla.org/buglist.cgi?list_id=4525985;classification=Components;query_format=advanced;bug_status=UNCONFIRMED;bug_status=NEW;bug_status=ASSIGNED;bug_status=REOPENED;component=mach;product=Core"},{"index":4,"title":"fhr P?","id":776,"parent":3,"dateAdded":1369677867827872,"lastModified":1369677872198140,"type":"text/x-moz-place","uri":"https://bugzilla.mozilla.org/buglist.cgi?product=Firefox%20Health%20Report&component=Client%3A%20Android&list_id=6644453"},{"index":5,"title":"a-s commits","id":569,"parent":3,"dateAdded":1331226693090050,"lastModified":1331226696920917,"type":"text/x-moz-place","uri":"https://github.com/mozilla-services/android-sync/commits/develop"},{"index":6,"title":"a-s pulls","id":570,"parent":3,"dateAdded":1331226707463538,"lastModified":1331226711400544,"type":"text/x-moz-place","uri":"https://github.com/mozilla-services/android-sync/pulls"},{"index":7,"title":"gmail","id":613,"parent":3,"dateAdded":1342198012357122,"lastModified":1342198020946677,"type":"text/x-moz-place","uri":"https://mail.google.com/mail/?shva=1#inbox"},{"index":8,"title":"crypto","id":677,"parent":3,"dateAdded":1352145611389997,"lastModified":1352766962874408,"livemark":1,"annos":[{"name":"placesInternal/READ_ONLY","flags":0,"expires":4,"mimeType":null,"type":1,"value":1},{"name":"livemark/feedURI","flags":0,"expires":4,"mimeType":null,"type":3,"value":"http://eprint.iacr.org/rss/rss.xml"},{"name":"livemark/siteURI","flags":0,"expires":4,"mimeType":null,"type":3,"value":"http://eprint.iacr.org/"}],"type":"text/x-moz-place-container","children":[]},{"index":9,"title":"file-desktop-bug","id":572,"parent":3,"dateAdded":1331683347630180,"lastModified":1331683353544712,"type":"text/x-moz-place","uri":"http://philikon.wordpress.com/2011/06/13/how-to-file-a-good-sync-bug/"},{"index":10,"title":"Bug List","id":684,"parent":3,"dateAdded":1352396973826197,"lastModified":1352396973826197,"type":"text/x-moz-place","uri":"https://bugzilla.mozilla.org/buglist.cgi?priority=P1;classification=Client%20Software;query_format=advanced;bug_status=UNCONFIRMED;bug_status=NEW;bug_status=ASSIGNED;bug_status=REOPENED;component=Android:%20Firefox%20Account;product=Mozilla%20Services;list_id=4909466"},{"index":11,"title":"fxe10s","id":783,"parent":3,"dateAdded":1370382384154087,"lastModified":1370382391226805,"type":"text/x-moz-place","uri":"https://bugzilla.mozilla.org/show_bug.cgi?id=fxe10s"},{"index":12,"title":"bzhome","id":787,"parent":3,"dateAdded":1371090808886470,"lastModified":1371090808886470,"type":"text/x-moz-place","uri":"http://harthur.github.io/bzhome/"}]},{"index":2,"title":"Tags","id":4,"parent":1,"dateAdded":1325734040863272,"lastModified":1346371636593604,"type":"text/x-moz-place-container","root":"tagsFolder","children":[{"title":"android","id":141,"parent":4,"dateAdded":1326218922125541,"lastModified":1326394245027110,"type":"text/x-moz-place-container","children":[{"title":"Services/NativeSync - MozillaWiki","id":142,"parent":141,"dateAdded":1326218922125878,"lastModified":1326218922125878,"type":"text/x-moz-place","uri":"https://wiki.mozilla.org/Services/NativeSync","charset":"UTF-8"},{"index":1,"title":"Coverage Report","id":279,"parent":141,"dateAdded":1326325077042971,"lastModified":1326325077042971,"type":"text/x-moz-place","uri":"file:///Users/ncalexan/Mozilla/Android/Devel/android-sync/target/site/cobertura/index.html","charset":"UTF-8"},{"index":2,"title":"a little madness » Blog Archive » Understanding the Android Build Process","id":347,"parent":141,"dateAdded":1326394245027110,"lastModified":1326394245027110,"type":"text/x-moz-place","uri":"http://www.alittlemadness.com/2010/06/07/understanding-the-android-build-process/","charset":"UTF-8"}]},{"index":1,"title":"native","id":143,"parent":4,"dateAdded":1326218922127478,"lastModified":1326218922127948,"type":"text/x-moz-place-container","children":[{"title":"Services/NativeSync - MozillaWiki","id":144,"parent":143,"dateAdded":1326218922127948,"lastModified":1326218922127948,"type":"text/x-moz-place","uri":"https://wiki.mozilla.org/Services/NativeSync","charset":"UTF-8"}]},{"index":2,"title":"sync","id":145,"parent":4,"dateAdded":1326218922129316,"lastModified":1326325077042303,"type":"text/x-moz-place-container","children":[{"title":"Services/NativeSync - MozillaWiki","id":146,"parent":145,"dateAdded":1326218922129662,"lastModified":1326218922129662,"type":"text/x-moz-place","uri":"https://wiki.mozilla.org/Services/NativeSync","charset":"UTF-8"},{"index":1,"title":"Services/Sync/Snippets - MozillaWiki","id":212,"parent":145,"dateAdded":1326244096899931,"lastModified":1326244096899931,"type":"text/x-moz-place","uri":"https://wiki.mozilla.org/Services/Sync/Snippets","charset":"UTF-8"},{"index":2,"title":"Coverage Report","id":278,"parent":145,"dateAdded":1326325077042303,"lastModified":1326325077042303,"type":"text/x-moz-place","uri":"file:///Users/ncalexan/Mozilla/Android/Devel/android-sync/target/site/cobertura/index.html","charset":"UTF-8"}]},{"index":3,"title":"mozilla","id":147,"parent":4,"dateAdded":1326218922130789,"lastModified":1326325077040643,"type":"text/x-moz-place-container","children":[{"title":"Services/NativeSync - MozillaWiki","id":148,"parent":147,"dateAdded":1326218922130991,"lastModified":1326218922130991,"type":"text/x-moz-place","uri":"https://wiki.mozilla.org/Services/NativeSync","charset":"UTF-8"},{"index":1,"title":"Services/Sync/Snippets - MozillaWiki","id":211,"parent":147,"dateAdded":1326244096831742,"lastModified":1326244096831742,"type":"text/x-moz-place","uri":"https://wiki.mozilla.org/Services/Sync/Snippets","charset":"UTF-8"},{"index":2,"title":"Coverage Report","id":277,"parent":147,"dateAdded":1326325077040643,"lastModified":1326325077040643,"type":"text/x-moz-place","uri":"file:///Users/ncalexan/Mozilla/Android/Devel/android-sync/target/site/cobertura/index.html","charset":"UTF-8"}]},{"index":4,"title":"javascript","id":213,"parent":4,"dateAdded":1326244096900597,"lastModified":1326244096900860,"type":"text/x-moz-place-container","children":[{"title":"Services/Sync/Snippets - MozillaWiki","id":214,"parent":213,"dateAdded":1326244096900860,"lastModified":1326244096900860,"type":"text/x-moz-place","uri":"https://wiki.mozilla.org/Services/Sync/Snippets","charset":"UTF-8"}]},{"index":5,"title":"snippet","id":215,"parent":4,"dateAdded":1326244096901455,"lastModified":1326244096901704,"type":"text/x-moz-place-container","children":[{"title":"Services/Sync/Snippets - MozillaWiki","id":216,"parent":215,"dateAdded":1326244096901704,"lastModified":1326244096901704,"type":"text/x-moz-place","uri":"https://wiki.mozilla.org/Services/Sync/Snippets","charset":"UTF-8"}]},{"index":6,"title":"code","id":280,"parent":4,"dateAdded":1326325077043543,"lastModified":1326325077043791,"type":"text/x-moz-place-container","children":[{"title":"Coverage Report","id":281,"parent":280,"dateAdded":1326325077043791,"lastModified":1326325077043791,"type":"text/x-moz-place","uri":"file:///Users/ncalexan/Mozilla/Android/Devel/android-sync/target/site/cobertura/index.html","charset":"UTF-8"}]},{"index":7,"title":"coverage","id":282,"parent":4,"dateAdded":1326325077044462,"lastModified":1326325077044723,"type":"text/x-moz-place-container","children":[{"title":"Coverage Report","id":283,"parent":282,"dateAdded":1326325077044723,"lastModified":1326325077044723,"type":"text/x-moz-place","uri":"file:///Users/ncalexan/Mozilla/Android/Devel/android-sync/target/site/cobertura/index.html","charset":"UTF-8"}]},{"index":8,"title":"cobertura","id":284,"parent":4,"dateAdded":1326325077045302,"lastModified":1326325077045587,"type":"text/x-moz-place-container","children":[{"title":"Coverage Report","id":285,"parent":284,"dateAdded":1326325077045587,"lastModified":1326325077045587,"type":"text/x-moz-place","uri":"file:///Users/ncalexan/Mozilla/Android/Devel/android-sync/target/site/cobertura/index.html","charset":"UTF-8"}]},{"index":9,"title":"build","id":348,"parent":4,"dateAdded":1326394245059448,"lastModified":1326394245059795,"type":"text/x-moz-place-container","children":[{"title":"a little madness » Blog Archive » Understanding the Android Build Process","id":349,"parent":348,"dateAdded":1326394245059795,"lastModified":1326394245059795,"type":"text/x-moz-place","uri":"http://www.alittlemadness.com/2010/06/07/understanding-the-android-build-process/","charset":"UTF-8"}]},{"index":10,"title":"process","id":350,"parent":4,"dateAdded":1326394245060425,"lastModified":1326394245060693,"type":"text/x-moz-place-container","children":[{"title":"a little madness » Blog Archive » Understanding the Android Build Process","id":351,"parent":350,"dateAdded":1326394245060693,"lastModified":1326394245060693,"type":"text/x-moz-place","uri":"http://www.alittlemadness.com/2010/06/07/understanding-the-android-build-process/","charset":"UTF-8"}]},{"index":11,"title":"bz","id":631,"parent":4,"dateAdded":1346371636593604,"lastModified":1346371636594747,"type":"text/x-moz-place-container","children":[{"title":null,"id":632,"parent":631,"dateAdded":1346371636594747,"lastModified":1346371636594747,"type":"text/x-moz-place","uri":"https://bugzilla.mozilla.org/show_bug.cgi?id=%s"}]}]},{"index":3,"title":"Unsorted Bookmarks","id":5,"parent":1,"dateAdded":1325734040866977,"lastModified":1325734040936742,"type":"text/x-moz-place-container","root":"unfiledBookmarksFolder","children":[]}]}